MAMEToolkit-1.1.0.dist-info/METADATA
MAMEToolkit-1.1.0.dist-info/RECORD
MAMEToolkit-1.1.0.dist-info/WHEEL
MAMEToolkit-1.1.0.dist-info/top_level.txt
MAMEToolkit/__init__.py
MAMEToolkit/emulator/BitmapFormat.py
MAMEToolkit/emulator/__init__.py
MAMEToolkit/emulator/Emulator.py
MAMEToolkit/emulator/Action.py
MAMEToolkit/emulator/StreamGobbler.py
MAMEToolkit/emulator/Address.py
MAMEToolkit/emulator/Console.py
MAMEToolkit/emulator/pipes/__init__.py
MAMEToolkit/emulator/pipes/Pipe.py
MAMEToolkit/emulator/pipes/DataPipe.py
MAMEToolkit/emulator/mame/mame
MAMEToolkit/emulator/mame/fonts/fonts.conf
MAMEToolkit/emulator/mame/fonts/fonts.dtd
MAMEToolkit/emulator/mame/fonts/conf.d/60-latin.conf
MAMEToolkit/emulator/mame/fonts/conf.d/30-urw-aliases.conf
MAMEToolkit/emulator/mame/fonts/conf.d/80-delicious.conf
MAMEToolkit/emulator/mame/fonts/conf.d/49-sansserif.conf
MAMEToolkit/emulator/mame/fonts/conf.d/30-metric-aliases.conf
MAMEToolkit/emulator/mame/fonts/conf.d/51-local.conf
MAMEToolkit/emulator/mame/fonts/conf.d/25-no-bitmap-dist.conf
MAMEToolkit/emulator/mame/fonts/conf.d/69-unifont.conf
MAMEToolkit/emulator/mame/fonts/conf.d/20-unhint-small-vera.conf
MAMEToolkit/emulator/mame/fonts/conf.d/90-synthetic.conf
MAMEToolkit/emulator/mame/fonts/conf.d/20-fix-globaladvance.conf
MAMEToolkit/emulator/mame/fonts/conf.d/25-unhint-nonlatin.conf
MAMEToolkit/emulator/mame/fonts/conf.d/40-nonlatin.conf
MAMEToolkit/emulator/mame/fonts/conf.d/65-fonts-persian.conf
MAMEToolkit/emulator/mame/fonts/conf.d/45-latin.conf
MAMEToolkit/emulator/mame/fonts/conf.d/65-nonlatin.conf
MAMEToolkit/emulator/mame/fonts/conf.d/50-user.conf
MAMEToolkit/emulator/mame/fonts/conf.avail/60-latin.conf
MAMEToolkit/emulator/mame/fonts/conf.avail/10-unhinted.conf
MAMEToolkit/emulator/mame/fonts/conf.avail/70-yes-bitmaps.conf
MAMEToolkit/emulator/mame/fonts/conf.avail/10-autohint.conf
MAMEToolkit/emulator/mame/fonts/conf.avail/10-sub-pixel-bgr.conf
MAMEToolkit/emulator/mame/fonts/conf.avail/30-urw-aliases.conf
MAMEToolkit/emulator/mame/fonts/conf.avail/80-delicious.conf
