Metadata-Version: 2.1
Name: MAMEToolkit
Version: 1.1.0
Summary: A library to train your RL algorithms against MAME arcade games on Linux
Home-page: https://github.com/M-J-Murray/MAMEToolkit
Author: Michael Murray
Author-email: m.j.murray123@gmail.com
License: UNKNOWN
Platform: UNKNOWN
Classifier: Programming Language :: Python :: 3
Classifier: License :: OSI Approved :: MIT License
Classifier: Operating System :: POSIX :: Linux
Requires-Dist: numpy
